{
  "indexes": [
    {
      "collectionGroup": "dreams",
      "queryScope": "COLLECTION",
      "fields": [
        { "fieldPath": "userId", "order": "ASCENDING" },
        { "fieldPath": "recordedAt", "order": "DESCENDING" }
      ]
    },
    {
      "collectionGroup": "publicDreams",
      "queryScope": "COLLECTION",
      "fields": [
        { "fieldPath": "deletedAt", "order": "ASCENDING" },
        { "fieldPath": "recordedAt", "order": "DESCENDING" }
      ]
    },
    {
      "collectionGroup": "announcements",
      "queryScope": "COLLECTION",
      "fields": [
        { "fieldPath": "published", "order": "ASCENDING" },
        { "fieldPath": "createdAt", "order": "DESCENDING" }
      ]
    },
    {
      "collectionGroup": "userReadAnnouncements",
      "queryScope": "COLLECTION",
      "fields": [
        { "fieldPath": "userId", "order": "ASCENDING" }
      ]
    }
  ],
  "fieldOverrides": []
}
